injectable/__init__.py
injectable/common_utils.py
injectable/constants.py
injectable/autowiring/__init__.py
injectable/autowiring/autowired_decorator.py
injectable/autowiring/autowired_type.py
injectable/autowiring/autowiring_utils.py
injectable/container/__init__.py
injectable/container/injectable.py
injectable/container/injection_container.py
injectable/container/load_injection_container.py
injectable/container/namespace.py
injectable/errors/__init__.py
injectable/errors/autowiring_error.py
injectable/errors/injectable_load_error.py
injectable/errors/injection_error.py
injectable/injection/__init__.py
injectable/injection/inject.py
injectable/injection/injectable_decorator.py
injectable/injection/injectable_factory_decorator.py
injectable/injection/injection_utils.py
injectable/testing/__init__.py
injectable/testing/clear_injectables_util.py
injectable/testing/register_injectables_util.py
injectable/testing/reset_injection_container_util.py
injectable-4.0.1.dist-info/LICENSE
injectable-4.0.1.dist-info/WHEEL
injectable-4.0.1.dist-info/METADATA
injectable-4.0.1.dist-info/RECORD
