Metadata-Version: 2.1
Name: injectable
Version: 4.0.1
Summary: Injectable is an elegant and simple Dependency Injection framework built with Heart and designed for Humans.
Author-email: Rodrigo Oliveira <oliveira.rodrigo.m@gmail.com>
Requires-Python: >= 3.9
Classifier: Intended Audience :: Developers
Classifier: License :: OSI Approved :: MIT License
Classifier: Operating System :: OS Independent
Classifier: Operating System :: Microsoft :: Windows
Classifier: Operating System :: MacOS
Classifier: Operating System :: POSIX
Classifier: Programming Language :: Python
Classifier: Programming Language :: Python :: 3
Classifier: Programming Language :: Python :: 3.9
Classifier: Programming Language :: Python :: 3.10
Classifier: Programming Language :: Python :: 3.11
Classifier: Programming Language :: Python :: 3.12
Classifier: Programming Language :: Python :: 3 :: Only
Classifier: Programming Language :: Python :: Implementation :: CPython
Classifier: Development Status :: 5 - Production/Stable
Classifier: Intended Audience :: Developers
Classifier: Topic :: Software Development :: Libraries :: Application Frameworks
Classifier: Typing :: Typed
Requires-Dist: lazy-object-proxy ~= 1.6
Requires-Dist: pycollect ~= 0.2
Requires-Dist: parameters-validation ~= 1.2
Requires-Dist: cached-property ~= 1.5
Requires-Dist: typing-inspect ~= 0.7
Requires-Dist: bump2version ~= 1.0 ; extra == "build"
Requires-Dist: build ~= 1.2.1 ; extra == "build"
Requires-Dist: flit ~= 3.9.0 ; extra == "build"
Requires-Dist: sphinx ~= 4.1 ; extra == "docs"
Requires-Dist: sphinx_py3doc_enhanced_theme ~= 2.4 ; extra == "docs"
Requires-Dist: pytest-runner ~= 5.3 ; extra == "test"
Requires-Dist: testfixtures ~= 6.18 ; extra == "test"
Requires-Dist: pytest ~= 6.2 ; extra == "test"
Requires-Dist: pytest-mock ~= 3.6 ; extra == "test"
Requires-Dist: pytest-cov ~= 2.12 ; extra == "test"
Requires-Dist: coveralls ~= 3.2 ; extra == "test"
Requires-Dist: black ~= 24.4.2 ; extra == "test"
Requires-Dist: flake8 ~= 7.1.0 ; extra == "test"
Project-URL: changelog, https://injectable.readthedocs.io/en/latest/changelog.html
Project-URL: homepage, https://injectable.readthedocs.io/en/latest/
Project-URL: issues, https://github.com/roo-oliv/injectable/issues
Project-URL: source, https://github.com/roo-oliv/injectable
Provides-Extra: build
Provides-Extra: docs
Provides-Extra: test
